queuery_client/__init__.py
queuery_client/cast.py
queuery_client/client.py
queuery_client/exceptions.py
queuery_client/py.typed
queuery_client/queuery_client.py
queuery_client/response.py
queuery_client/util.py
queuery_client-1.1.1.dist-info/LICENSE
queuery_client-1.1.1.dist-info/METADATA
queuery_client-1.1.1.dist-info/WHEEL
queuery_client-1.1.1.dist-info/RECORD
