Metadata-Version: 2.1
Name: queuery-client
Version: 1.1.1
Summary: Queuery Redshift HTTP API Client for Python
Home-page: https://github.com/bricolages/queuery_client_python
License: MIT
Author: altescy
Author-email: yasuhiro-yamaguchi@cookpad.com
Requires-Python: >=3.8,<4.0
Classifier: License :: OSI Approved :: MIT License
Classifier: Programming Language :: Python :: 3
Classifier: Programming Language :: Python :: 3.8
Classifier: Programming Language :: Python :: 3.9
Classifier: Programming Language :: Python :: 3.10
Classifier: Programming Language :: Python :: 3.11
Classifier: Programming Language :: Python :: 3.12
Classifier: Programming Language :: Python :: 3.13
Provides-Extra: all
Provides-Extra: pandas
Requires-Dist: numpy (>=1.2,<3.0) ; python_version >= "3.8" and python_version < "3.13"
Requires-Dist: numpy (>=2.0.1,<3.0) ; python_version >= "3.13"
Requires-Dist: python-dateutil (>=2.8,<3.0)
Requires-Dist: requests (>=2.25,<3.0)
